pytype/__init__.py
pytype/__main__.py
pytype/__version__.py
pytype/abstract.py
pytype/abstract_test.py
pytype/abstract_utils.py
pytype/abstract_utils_test.py
pytype/analyze.py
pytype/annotations_util.py
pytype/attribute.py
pytype/attribute_test.py
pytype/blocks.py
pytype/blocks_test.py
pytype/class_mixin.py
pytype/compare.py
pytype/compare_test.py
pytype/compat.py
pytype/compat_test.py
pytype/config.py
pytype/config_test.py
pytype/constant_folding.py
pytype/constant_folding_test.py
pytype/convert.py
pytype/convert_structural.py
pytype/convert_test.py
pytype/datatypes.py
pytype/datatypes_test.py
pytype/debug.py
pytype/debug_test.py
pytype/directors.py
pytype/directors_test.py
pytype/errors.py
pytype/errors_test.py
pytype/file_utils.py
pytype/file_utils_test.py
pytype/function.py
pytype/imports_map_loader.py
pytype/imports_map_loader_test.py
pytype/io.py
pytype/io_test.py
pytype/load_pytd.py
pytype/load_pytd_test.py
pytype/matcher.py
pytype/matcher_test.py
pytype/metaclass.py
pytype/metrics.py
pytype/metrics_test.py
pytype/mixin.py
pytype/mixin_test.py
pytype/module_utils.py
pytype/module_utils_test.py
pytype/output.py
pytype/overlay.py
pytype/overlay_dict.py
pytype/overlay_utils.py
pytype/pytype_source_utils.py
pytype/pytype_source_utils_test.py
pytype/single.py
pytype/single_test.py
pytype/special_builtins.py
pytype/state.py
pytype/state_test.py
pytype/typegraph_metrics_test.py
pytype/utils.py
pytype/utils_test.py
pytype/vm.py
pytype/vm_test.py
pytype/ast/__init__.py
pytype/ast/debug.py
pytype/ast/visitor.py
pytype/ast/visitor_test.py
pytype/overlays/__init__.py
pytype/overlays/abc_overlay.py
pytype/overlays/asyncio_types_overlay.py
pytype/overlays/attr_overlay.py
pytype/overlays/chex_overlay.py
pytype/overlays/classgen.py
pytype/overlays/collections_overlay.py
pytype/overlays/collections_overlay_test.py
pytype/overlays/dataclass_overlay.py
pytype/overlays/enum_overlay.py
pytype/overlays/flax_overlay.py
pytype/overlays/future_overlay.py
pytype-2021.8.11.dist-info/LICENSE
pytype-2021.8.11.dist-info/METADATA
pytype-2021.8.11.dist-info/WHEEL
pytype-2021.8.11.dist-info/entry_points.txt
pytype-2021.8.11.dist-info/top_level.txt
pytype-2021.8.11.dist-info/RECORD
