Metadata-Version: 2.1
Name: pytype
Version: 2021.8.11
Summary: Python type inferencer
Home-page: https://google.github.io/pytype
Maintainer: Google
Maintainer-email: pytype@googlegroups.com
License: Apache 2.0
Project-URL: Code, https://github.com/google/pytype
Project-URL: Issue Tracker, https://github.com/google/pytype/issues
Project-URL: Documentation, https://google.github.io/pytype
Platform: UNKNOWN
Classifier: Development Status :: 5 - Production/Stable
Classifier: Intended Audience :: Developers
Classifier: License :: OSI Approved :: Apache Software License
Classifier: Programming Language :: Python
Classifier: Programming Language :: Python :: 3.6
Classifier: Programming Language :: Python :: 3.7
Classifier: Programming Language :: Python :: 3.8
Classifier: Programming Language :: Python :: 3.9
Classifier: Programming Language :: Python :: Implementation :: CPython
Classifier: Topic :: Software Development
Requires-Python: <3.10,>=3.6
